more_sso/__init__.py
more_sso/cache.py
more_sso/config.py
more_sso/decorators.py
more_sso/exceptions.py
more_sso/permissions.py
more_sso/validator.py
more_sso_auth-1.4.2.dist-info/licenses/LICENSE
more_sso_auth-1.4.2.dist-info/METADATA
more_sso_auth-1.4.2.dist-info/WHEEL
more_sso_auth-1.4.2.dist-info/top_level.txt
more_sso_auth-1.4.2.dist-info/RECORD
