Metadata-Version: 2.4
Name: more-sso-auth
Version: 1.4.2
Summary: A lightweight and extensible Single Sign-On (SSO) authentication library for Python.
Author-email: chalapathy v <chalapathyv57@gmail.com>
License: MIT
Requires-Python: >=3.8
License-File: LICENSE
Requires-Dist: cryptography==46.0.3
Dynamic: license-file
